mopyregtest/__init__.py
mopyregtest/cli.py
mopyregtest/generator.py
mopyregtest/metrics.py
mopyregtest/modelicaregressiontest.py
mopyregtest/utils.py
mopyregtest/templates/omc/model_import.mos.template
mopyregtest/templates/omc/model_simulate.mos.template
MoPyRegtest-0.5.1.dist-info/LICENSE
MoPyRegtest-0.5.1.dist-info/METADATA
MoPyRegtest-0.5.1.dist-info/WHEEL
MoPyRegtest-0.5.1.dist-info/entry_points.txt
MoPyRegtest-0.5.1.dist-info/top_level.txt
MoPyRegtest-0.5.1.dist-info/RECORD
