Metadata-Version: 2.1
Name: MoPyRegtest
Version: 0.5.1
Summary: A Python enabled simple regression testing framework for Modelica models
Home-page: https://github.com/pstelzig/mopyregtest
Author: Philipp Emanuel Stelzig
Classifier: Programming Language :: Python :: 3
Classifier: License :: OSI Approved :: MIT License
Classifier: Operating System :: Microsoft :: Windows :: Windows 10
Classifier: Operating System :: POSIX :: Linux
Requires-Python: >=3.8
License-File: LICENSE
Requires-Dist: numpy
Requires-Dist: pandas
